{"higher_level": [], "index": "protection-from-energy", "name": "Protection From Energy", "desc": ["For the duration, the willing creature you touch has resistance to one damage type of your choice: acid, cold, fire, lightning, or thunder."], "range": "Touch", "components": ["V", "S"], "ritual": false, "duration": "Up to 1 hour", "concentration": true, "casting_time": "1 action", "level": 3, "school": {"index": "abjuration", "name": "Abjuration", "url": "/api/magic-schools/abjuration"}, "classes": [{"index": "cleric", "name": "Cleric", "url": "/api/classes/cleric"}, {"index": "druid", "name": "Druid", "url": "/api/classes/druid"}, {"index": "ranger", "name": "Ranger", "url": "/api/classes/ranger"}, {"index": "sorcerer", "name": "Sorcerer", "url": "/api/classes/sorcerer"}, {"index": "wizard", "name": "Wizard", "url": "/api/classes/wizard"}], "subclasses": [{"index": "lore", "name": "Lore", "url": "/api/subclasses/lore"}, {"index": "land", "name": "Land", "url": "/api/subclasses/land"}], "url": "/api/spells/protection-from-energy"}