{"index": "sorcerer", "name": "Sorcerer", "hit_die": 6, "proficiency_choices": [{"choose": 2, "type": "proficiencies", "from": [{"index": "skill-arcana", "name": "Skill: Arcana", "url": "/api/proficiencies/skill-arcana"}, {"index": "skill-deception", "name": "Skill: Deception", "url": "/api/proficiencies/skill-deception"}, {"index": "skill-insight", "name": "Skill: Insight", "url": "/api/proficiencies/skill-insight"}, {"index": "skill-intimidation", "name": "Skill: Intimidation", "url": "/api/proficiencies/skill-intimidation"}, {"index": "skill-persuasion", "name": "Skill: Persuasion", "url": "/api/proficiencies/skill-persuasion"}, {"index": "skill-religion", "name": "Skill: Religion", "url": "/api/proficiencies/skill-religion"}]}], "proficiencies": [{"index": "daggers", "name": "Daggers", "url": "/api/proficiencies/daggers"}, {"index": "quarterstaffs", "name": "Quarterstaffs", "url": "/api/proficiencies/quarterstaffs"}, {"index": "darts", "name": "Darts", "url": "/api/proficiencies/darts"}, {"index": "slings", "name": "Slings", "url": "/api/proficiencies/slings"}], "saving_throws": [{"index": "con", "name": "CON", "url": "/api/ability-scores/con"}, {"index": "cha", "name": "CHA", "url": "/api/ability-scores/cha"}], "starting_equipment": "/api/starting-equipment/sorcerer", "class_levels": "/api/classes/sorcerer/levels", "subclasses": [{"index": "draconic", "name": "Draconic", "url": "/api/subclasses/draconic"}], "spellcasting": "/api/spellcasting/sorcerer", "spells": "/api/classes/sorcerer/spells", "url": "/api/classes/sorcerer"}