{"special": [], "index": "spyglass", "name": "Spyglass", "equipment_category": {"index": "adventuring-gear", "name": "Adventuring Gear", "url": "/api/equipment-categories/adventuring-gear"}, "gear_category": {"index": "standard-gear", "name": "Standard Gear", "url": "/api/equipment-categories/standard-gear"}, "cost": {"quantity": 1000, "unit": "gp"}, "weight": 1, "desc": ["Objects viewed through a spyglass are magnified to twice their size."], "url": "/api/equipment/spyglass", "contents": [], "properties": []}