{"index": "shatter", "name": "Shatter", "desc": ["A sudden loud ringing noise, painfully intense, erupts from a point of your choice within range. Each creature in a 10-foot-radius sphere centered on that point must make a Constitution saving throw. A creature takes 3d8 thunder damage on a failed save, or half as much damage on a successful one. A creature made of inorganic material such as stone, crystal, or metal has disadvantage on this saving throw.", "A non-magical item that is not worn or carried also suffers damage if it is in the area of the spell."], "higher_level": ["When you cast this spell using a 3 or higher level spell slot, the damage of the spell increases by 1d8 for each level of higher spell slot 2."], "range": "60 feet", "components": ["V", "S", "M"], "material": "A burst of mica.", "ritual": false, "duration": "Instantaneous", "concentration": false, "casting_time": "1 action", "level": 2, "damage": {"damage_type": {"index": "thunder", "name": "Thunder", "url": "/api/damage-types/thunder"}, "damage_at_slot_level": {"2": "3d8", "3": "4d8", "4": "5d8", "5": "6d8", "6": "7d8", "7": "8d8", "8": "9d8", "9": "10d8"}}, "dc": {"dc_type": {"index": "con", "name": "CON", "url": "/api/ability-scores/con"}, "dc_success": "half"}, "area_of_effect": {"type": "sphere", "size": 10}, "school": {"index": "evocation", "name": "Evocation", "url": "/api/magic-schools/evocation"}, "classes": [{"index": "bard", "name": "Bard", "url": "/api/classes/bard"}, {"index": "sorcerer", "name": "Sorcerer", "url": "/api/classes/sorcerer"}, {"index": "warlock", "name": "Warlock", "url": "/api/classes/warlock"}, {"index": "wizard", "name": "Wizard", "url": "/api/classes/wizard"}], "subclasses": [{"index": "lore", "name": "Lore", "url": "/api/subclasses/lore"}], "url": "/api/spells/shatter"}