{"index": "arcane-tradition", "class": {"index": "wizard", "name": "Wizard", "url": "/api/classes/wizard"}, "name": "Arcane Tradition", "level": 2, "desc": ["When you reach 2nd level, you choose an arcane tradition, shaping your practice of magic through one of eight schools: Abjuration, Conjuration, Divination, Enchantment, Evocation, Illusion, Necromancy, or Transmutation, all detailed at the end of the class description.", "Your choice grants you features at 2nd level and again at 6th, 10th, and 14th level."], "url": "/api/features/arcane-tradition"}